<breakPointInfo>
<package>
<name>keepassSafe</name>
<classFile>
<name>passwordSafe.java</name>
<lines>
<line>
<linenumber>652</linenumber>
<valid>1</valid>
<invalidTimes>0</invalidTimes>
</line>
<line>
<linenumber>661</linenumber>
<valid>1</valid>
<invalidTimes>0</invalidTimes>
</line>
<line>
<linenumber>648</linenumber>
<valid>1</valid>
<invalidTimes>0</invalidTimes>
</line>
<line>
<linenumber>650</linenumber>
<valid>1</valid>
<invalidTimes>0</invalidTimes>
</line>
<line>
<linenumber>653</linenumber>
<valid>1</valid>
<invalidTimes>0</invalidTimes>
</line>
</lines>
</classFile>
</package>
</breakPointInfo>
